_subsetsum.cpython-39-x86_64-linux-gnu.so
subsetsum-0.0.2.dist-info/METADATA
subsetsum-0.0.2.dist-info/WHEEL
subsetsum-0.0.2.dist-info/RECORD
subsetsum-0.0.2.dist-info/LICENSE
subsetsum-0.0.2.dist-info/top_level.txt
subsetsum/__init__.py
