Metadata-Version: 2.1
Name: subsetsum
Version: 0.0.2
Summary: A Python module for finding all solutions to the SUBSET-SUM problem
Home-page: https://github.com/trevphil/subsetsum
Author: Trevor Phillips
Author-email: trevphil3@gmail.com
License: UNKNOWN
Platform: UNKNOWN
Requires-Python: >=3.6
Provides-Extra: test
License-File: LICENSE
